<mvc:View controllerName="proyectofinal.proyectofinal.controller.MainView" displayBlock="true"
    xmlns="sap.m"
    xmlns:mvc="sap.ui.core.mvc">
    <Page title="{i18n>MenuPrincipal}" class="sapMBarTitleStart">
        <content>
            <Panel id="page" headerText="{i18n>empleados}">
                <GenericTile headerImage="sap-icon://add-employee" class="sapUiTinyMarginBegin sapUiTinyMarginTop" press="onCrearEmpleado">
                    <TileContent footer="{i18n>crearEmpleado}"/>
                </GenericTile>
                <GenericTile headerImage="sap-icon://employee-lookup" class="sapUiTinyMarginBegin sapUiTinyMarginTop" press="onVerEmpleado">
                    <TileContent footer="{i18n>verEmpleado}"/>
                </GenericTile>
            </Panel>
            <Panel headerText="{i18n>pedido}">
                <GenericTile headerImage="sap-icon://signature" class="sapUiTinyMarginBegin sapUiTinyMarginTop" press="onFirmarPedidos">
                    <TileContent footer="{i18n>pedido}"/>
                </GenericTile>
            </Panel>
        </content>
    </Page>
</mvc:View>